CHANGELOG.rst
LICENSE
MANIFEST.in
README.rst
setup.cfg
setup.py
django_reversion_patchman.egg-info/PKG-INFO
django_reversion_patchman.egg-info/SOURCES.txt
django_reversion_patchman.egg-info/dependency_links.txt
django_reversion_patchman.egg-info/not-zip-safe
django_reversion_patchman.egg-info/requires.txt
django_reversion_patchman.egg-info/top_level.txt
docs/admin.rst
docs/api.rst
docs/changelog.rst
docs/commands.rst
docs/common-problems.rst
docs/conf.py
docs/django-versions.rst
docs/errors.rst
docs/index.rst
docs/middleware.rst
docs/signals.rst
docs/views.rst
docs/_include/admin.rst
docs/_include/create-revision-args.rst
docs/_include/create-revision-manage-manually.rst
docs/_include/create-revision-using.rst
docs/_include/model-db-arg.rst
docs/_include/post-register.rst
docs/_include/signal-args.rst
docs/_include/throws-registration-error.rst
docs/_include/throws-revert-error.rst
docs/_include/throws-revision-error.rst
reversion/__init__.py
reversion/admin.py
reversion/compat.py
reversion/errors.py
reversion/middleware.py
reversion/models.py
reversion/revisions.py
reversion/signals.py
reversion/views.py
reversion/locale/ar/LC_MESSAGES/django.mo
reversion/locale/ar/LC_MESSAGES/django.po
reversion/locale/cs/LC_MESSAGES/django.mo
reversion/locale/cs/LC_MESSAGES/django.po
reversion/locale/da/LC_MESSAGES/django.mo
reversion/locale/da/LC_MESSAGES/django.po
reversion/locale/de/LC_MESSAGES/django.mo
reversion/locale/de/LC_MESSAGES/django.po
reversion/locale/es/LC_MESSAGES/django.mo
reversion/locale/es/LC_MESSAGES/django.po
reversion/locale/es_AR/LC_MESSAGES/django.mo
reversion/locale/es_AR/LC_MESSAGES/django.po
reversion/locale/fr/LC_MESSAGES/django.mo
reversion/locale/fr/LC_MESSAGES/django.po
reversion/locale/he/LC_MESSAGES/django.mo
reversion/locale/he/LC_MESSAGES/django.po
reversion/locale/it/LC_MESSAGES/django.mo
reversion/locale/it/LC_MESSAGES/django.po
reversion/locale/nb/LC_MESSAGES/django.mo
reversion/locale/nb/LC_MESSAGES/django.po
reversion/locale/nl/LC_MESSAGES/django.mo
reversion/locale/nl/LC_MESSAGES/django.po
reversion/locale/pl/LC_MESSAGES/django.mo
reversion/locale/pl/LC_MESSAGES/django.po
reversion/locale/pt_BR/LC_MESSAGES/django.mo
reversion/locale/pt_BR/LC_MESSAGES/django.po
reversion/locale/ru/LC_MESSAGES/django.mo
