Metadata-Version: 1.1
Name: django-reversion-patchman
Version: 2.1.1
Summary: An extension to the Django web framework that provides version control for model instances. Patchman version.
Home-page: https://github.com/PatchmanBV/django-reversion
Author: Patchman B.V.
Author-email: info@patchman.co
License: BSD
Platform: UNKNOWN
Classifier: Development Status :: 5 - Production/Stable
Classifier: Environment :: Web Environment
Classifier: Intended Audience :: Developers
Classifier: License :: OSI Approved :: BSD License
Classifier: Operating System :: OS Independent
Classifier: Programming Language :: Python
Classifier: Programming Language :: Python :: 2.7
Classifier: Programming Language :: Python :: 3.4
Classifier: Programming Language :: Python :: 3.5
Classifier: Framework :: Django
